README.rst
setup.py
ampcountpy/__init__.py
ampcountpy/__main__.py
ampcountpy/ampcount.py
ampcountpy.egg-info/PKG-INFO
ampcountpy.egg-info/SOURCES.txt
ampcountpy.egg-info/dependency_links.txt
ampcountpy.egg-info/entry_points.txt
ampcountpy.egg-info/top_level.txt
ampcountpy.egg-info/zip-safe