Metadata-Version: 1.1
Name: ampcountpy
Version: 0.2.0
Summary: Some functions to count the expected amplifications for genomic regions given a set of primer binding locations for a multiple displacement amplification reaction.
Home-page: http://github.com/sherrillmix/ampCountPy
Author: Scott Sherrill-Mix
Author-email: shescott@upenn.edu
License: GPL 3
Platform: UNKNOWN
Classifier: Topic :: Scientific/Engineering :: Bio-Informatics
Classifier: Intended Audience :: Science/Research
Classifier: License :: OSI Approved :: GNU General Public License (GPL)
